payme/__init__.py
payme/admin.cpython-312-darwin.so
payme/apps.cpython-312-darwin.so
payme/const.cpython-312-darwin.so
payme/licensing.cpython-312-darwin.so
payme/models.cpython-312-darwin.so
payme/urls.cpython-312-darwin.so
payme/util.cpython-312-darwin.so
payme/classes/__init__.py
payme/classes/cards.cpython-312-darwin.so
payme/classes/client.py
payme/classes/http.cpython-312-darwin.so
payme/classes/initializer.cpython-312-darwin.so
payme/classes/receipts.cpython-312-darwin.so
payme/exceptions/__init__.py
payme/exceptions/general.cpython-312-darwin.so
payme/exceptions/webhook.cpython-312-darwin.so
payme/migrations/0001_initial.py
payme/migrations/0002_paymetransactions_fiscal_data.py
payme/migrations/0003_alter_paymetransactions_fiscal_data.py
payme/migrations/0004_alter_paymetransactions_account_id.py
payme/migrations/0005_alter_paymetransactions_amount.py
payme/migrations/__init__.py
payme/types/__init__.py
payme/types/request/__init__.py
payme/types/response/__init__.py
payme/types/response/cards.py
payme/types/response/receipts.py
payme/types/response/webhook.py
payme/views/__init__.py
payme/views/base.cpython-312-darwin.so
payme/views/payme.py
payme_pkg-3.3.2.dist-info/licenses/LICENSE.txt
payme_pkg-3.3.2.dist-info/METADATA
payme_pkg-3.3.2.dist-info/WHEEL
payme_pkg-3.3.2.dist-info/top_level.txt
payme_pkg-3.3.2.dist-info/RECORD
