Metadata-Version: 2.4
Name: payme_pkg
Version: 3.3.2
Home-page: https://github.com/Muhammadali-Akbarov/payme-pkg
Author: Muhammadali Akbarov
Author-email: muhammadali17abc@gmail.com
License: MIT
Keywords: paymeuz paycomuz payme-merchant merchant-api subscribe-api payme-pkg payme-api
License-File: LICENSE.txt
Requires-Dist: requests==2.*
Requires-Dist: dataclasses==0.*; python_version < "3.7"
Requires-Dist: djangorestframework==3.*
Requires-Dist: environs>=9.0.0
Dynamic: author
Dynamic: author-email
Dynamic: description
Dynamic: description-content-type
Dynamic: home-page
Dynamic: keywords
Dynamic: license
Dynamic: license-file
Dynamic: requires-dist
